AUTHORS
CHANGES
LICENSE
MANIFEST.in
Makefile
README.rst
requirements.pip
setup.py
sample_data_utils/__init__.py
sample_data_utils/__init__.py.orig
sample_data_utils/api.py
sample_data_utils/conf.py
sample_data_utils/date.py
sample_data_utils/exception.py
sample_data_utils/geo.py
sample_data_utils/money.py
sample_data_utils/net.py
sample_data_utils/numeric.py
sample_data_utils/people.py
sample_data_utils/sample.py
sample_data_utils/storage.py
sample_data_utils/text.py
sample_data_utils/utils.py
sample_data_utils.egg-info/PKG-INFO
sample_data_utils.egg-info/SOURCES.txt
sample_data_utils.egg-info/dependency_links.txt
sample_data_utils.egg-info/requires.txt
sample_data_utils.egg-info/top_level.txt
sample_data_utils/data/countryInfo.txt
sample_data_utils/data/iso_codes.csv
sample_data_utils/data/de/firstnames_f.txt
sample_data_utils/data/de/firstnames_m.txt
sample_data_utils/data/de/lastnames.txt
sample_data_utils/data/de/loremipsum.txt
sample_data_utils/data/de/ms.txt
sample_data_utils/data/de/title.txt
sample_data_utils/data/en/address.txt
sample_data_utils/data/en/continents.txt
sample_data_utils/data/en/continents_countries.txt
sample_data_utils/data/en/firstnames_f.txt
sample_data_utils/data/en/firstnames_m.txt
sample_data_utils/data/en/lastnames.txt
sample_data_utils/data/en/loremipsum.txt
sample_data_utils/data/en/ms.txt
sample_data_utils/data/en/title.txt
sample_data_utils/data/es/firstnames_f.txt
sample_data_utils/data/es/firstnames_m.txt
sample_data_utils/data/es/lastnames.txt
sample_data_utils/data/es/loremipsum.txt
sample_data_utils/data/es/ms.txt
sample_data_utils/data/es/title.txt
sample_data_utils/data/fr/firstnames_f.txt
sample_data_utils/data/fr/firstnames_m.txt
sample_data_utils/data/fr/lastnames.txt
sample_data_utils/data/fr/loremipsum.txt
sample_data_utils/data/fr/ms.txt
sample_data_utils/data/fr/title.txt
sample_data_utils/data/gr/loremipsum.txt
sample_data_utils/data/il/loremipsum.txt
sample_data_utils/data/it/comuni.txt
sample_data_utils/data/it/firstnames_f.txt
sample_data_utils/data/it/firstnames_m.txt
sample_data_utils/data/it/lastnames.txt
sample_data_utils/data/it/loremipsum.txt
sample_data_utils/data/it/ms.txt
