Metadata-Version: 1.1
Name: sample-data-utils
Version: 0.5
Summary: Collections of utilities to create random "human readeable" sample data.
Home-page: https://github.com/saxix/sample-data-utils
Author: Stefano Apostolico
Author-email: s.apostolico@gmail.com
License: MIT
Platform: linux
Classifier: Operating System :: OS Independent
Classifier: Programming Language :: Python :: 2.7
Classifier: Programming Language :: Python :: 3.2
Classifier: Programming Language :: Python :: 3.3
Classifier: Intended Audience :: Developers
